daptools/LaTeXHelper.py
daptools/__init__.py
daptools/binUtils.py
daptools/cleanDir.py
daptools/fileHasher.py
daptools/generateSHA.py
daptools/logger.py
daptools/mathPhys.py
daptools/metar.py
daptools/myTools.py
daptools/randomPasswordGen.py
daptools/sphericalGeodesy.py
daptools/standardAtmosphere.py
daptools/testFile.py
daptools/unitsBatch.py
daptools/velikonoce.py
daptools-1.1.dist-info/LICENSE
daptools-1.1.dist-info/METADATA
daptools-1.1.dist-info/WHEEL
daptools-1.1.dist-info/RECORD
